pydiggs/.DS_Store
pydiggs/__init__.py
pydiggs/cli.py
pydiggs/dictionaries/DIGGSTestPropertyDefinitions.xml
pydiggs/dictionaries/properties.xml
pydiggs/pydiggs.py
pydiggs/schemas/.DS_Store
pydiggs/schemas/diggs-schema-2.5.a/.gitignore
pydiggs/schemas/diggs-schema-2.5.a/Complete.xsd
pydiggs/schemas/diggs-schema-2.5.a/Dictionary_diggs.xsd
pydiggs/schemas/diggs-schema-2.5.a/Example_2-DIGGS.XML
pydiggs/schemas/diggs-schema-2.5.a/Geotechnical.xsd
pydiggs/schemas/diggs-schema-2.5.a/Kernel.xsd
pydiggs/schemas/diggs-schema-2.5.a/LICENSE
pydiggs/schemas/diggs-schema-2.5.a/README.md
pydiggs/schemas/diggs-schema-2.5.a/glrProfile_diggs.xsd
pydiggs/schemas/diggs-schema-2.5.a/glrovProfile_diggs.xsd
pydiggs/schemas/diggs-schema-2.5.a/gml3.2Profile_diggs.xsd
pydiggs/schemas/diggs-schema-2.5.a/gml3.3Profile_diggs.xsd
pydiggs/schemas/diggs-schema-2.5.a/witsml/1.3.1.1/typ_baseType.xsd
pydiggs/schemas/diggs-schema-2.5.a/witsml/1.3.1.1/typ_catalog.xsd
pydiggs/schemas/diggs-schema-2.5.a/witsml/1.3.1.1/typ_dataTypes.xsd
pydiggs/schemas/diggs-schema-2.5.a/witsml/1.3.1.1/typ_measureType.xsd
pydiggs/schemas/diggs-schema-2.5.a/witsml/1.3.1.1/typ_quantityClass.xsd
pydiggs/schemas/diggs-schema-2.5.a/xlinks.xsd
pydiggs/schemas/diggs-schema-2.5.a/xml.xsd
pydiggs/schemas/diggs-schema-2.6/.gitignore
pydiggs/schemas/diggs-schema-2.6/BetaProcedures.xsd
pydiggs/schemas/diggs-schema-2.6/Construction.xsd
pydiggs/schemas/diggs-schema-2.6/Dictionary_diggs.xsd
pydiggs/schemas/diggs-schema-2.6/Diggs.xsd
pydiggs/schemas/diggs-schema-2.6/Diggs_geo.xsd
pydiggs/schemas/diggs-schema-2.6/Diggs_geo_deprecated.xsd
pydiggs/schemas/diggs-schema-2.6/Geophysics.xsd
pydiggs/schemas/diggs-schema-2.6/Geotechnical.xsd
pydiggs/schemas/diggs-schema-2.6/Kernel.xsd
pydiggs/schemas/diggs-schema-2.6/README.md
pydiggs/schemas/diggs-schema-2.6/TestProceduresAll.xsd
pydiggs/schemas/diggs-schema-2.6/glrProfile_diggs.xsd
pydiggs/schemas/diggs-schema-2.6/glrovProfile_diggs.xsd
pydiggs/schemas/diggs-schema-2.6/gml3.2Profile_diggs.xsd
pydiggs-0.1.5.dist-info/LICENSE
pydiggs-0.1.5.dist-info/METADATA
pydiggs-0.1.5.dist-info/WHEEL
pydiggs-0.1.5.dist-info/entry_points.txt
pydiggs-0.1.5.dist-info/RECORD
