Metadata-Version: 2.3
Name: pydiggs
Version: 0.1.5
Summary: A Python package for Data Interchange for Geotechnical and Geoenvironmental Specialists (DIGGS).
License: Apache-2.0
Author: xin.peng
Author-email: xin_peng@outlook.com
Requires-Python: >=3.10
Classifier: License :: OSI Approved :: Apache Software License
Classifier: Programming Language :: Python :: 3
Classifier: Programming Language :: Python :: 3.10
Classifier: Programming Language :: Python :: 3.11
Classifier: Programming Language :: Python :: 3.12
Classifier: Programming Language :: Python :: 3.13
Requires-Dist: lxml (>=5.3.0)
Requires-Dist: myst-parser (>=4.0.0)
Requires-Dist: rich (>=13.9.4)
